scratchnet/__init__.py
scratchnet/logger.py
scratchnet/packet.py
scratchnet/server.py
scratchnet-0.1.0.dist-info/LICENSE.txt
scratchnet-0.1.0.dist-info/METADATA
scratchnet-0.1.0.dist-info/WHEEL
scratchnet-0.1.0.dist-info/top_level.txt
scratchnet-0.1.0.dist-info/RECORD
