Metadata-Version: 2.1
Name: scratchnet
Version: 0.1.0
Summary: External server support for scratch projects.
Home-page: https://github.com/synicalmx/scratchnet
Download-URL: https://github.com/synicalmx/scratchnet/archive/scratchnet-0.1.0.tar.gz
Author: synicalmx
License: MIT
Keywords: scratch,server,multiplayer
Classifier: Development Status :: 3 - Alpha
Classifier: Intended Audience :: Developers
Classifier: Topic :: Software Development :: Build Tools
Classifier: License :: OSI Approved :: MIT License
Classifier: Programming Language :: Python :: 3
Classifier: Programming Language :: Python :: 3.4
Classifier: Programming Language :: Python :: 3.5
Classifier: Programming Language :: Python :: 3.6
License-File: LICENSE.txt
Requires-Dist: scratchconnect
Requires-Dist: profanity
Requires-Dist: requests
Requires-Dist: colorama
